colorir/__init__.py
colorir/__main__.py
colorir/color_class.py
colorir/color_format.py
colorir/config.py
colorir/gradient.py
colorir/palette.py
colorir/tkinter_utils.py
colorir/utils.py
colorir/builtin_palettes/accent.spalette
colorir/builtin_palettes/afmhot.spalette
colorir/builtin_palettes/ag_grnyl.spalette
colorir/builtin_palettes/ag_sunset.spalette
colorir/builtin_palettes/algae.spalette
colorir/builtin_palettes/alphabet.spalette
colorir/builtin_palettes/amp.spalette
colorir/builtin_palettes/antique.spalette
colorir/builtin_palettes/armyrose.spalette
colorir/builtin_palettes/autumn.spalette
colorir/builtin_palettes/balance.spalette
colorir/builtin_palettes/basic.palette
colorir/builtin_palettes/binary.spalette
colorir/builtin_palettes/blackbody.spalette
colorir/builtin_palettes/bluered.spalette
colorir/builtin_palettes/blues.spalette
colorir/builtin_palettes/blugrn.spalette
colorir/builtin_palettes/bluyl.spalette
colorir/builtin_palettes/bold.spalette
colorir/builtin_palettes/bone.spalette
colorir/builtin_palettes/brbg.spalette
colorir/builtin_palettes/bright.spalette
colorir/builtin_palettes/brwnyl.spalette
colorir/builtin_palettes/bugn.spalette
colorir/builtin_palettes/bupu.spalette
colorir/builtin_palettes/burg.spalette
colorir/builtin_palettes/burgyl.spalette
colorir/builtin_palettes/bwr.spalette
colorir/builtin_palettes/carnival.spalette
colorir/builtin_palettes/cividis.spalette
colorir/builtin_palettes/colorblind.spalette
colorir/builtin_palettes/cool.spalette
colorir/builtin_palettes/coolwarm.spalette
colorir/builtin_palettes/copper.spalette
colorir/builtin_palettes/crest.spalette
colorir/builtin_palettes/css.palette
colorir/builtin_palettes/cubehelix.spalette
colorir/builtin_palettes/curl.spalette
colorir/builtin_palettes/d3.spalette
colorir/builtin_palettes/dark.spalette
colorir/builtin_palettes/dark2.spalette
colorir/builtin_palettes/dark24.spalette
colorir/builtin_palettes/darkmint.spalette
colorir/builtin_palettes/deep.spalette
colorir-2.0.5.dist-info/LICENSE.txt
colorir-2.0.5.dist-info/METADATA
colorir-2.0.5.dist-info/WHEEL
colorir-2.0.5.dist-info/top_level.txt
colorir-2.0.5.dist-info/RECORD
