Metadata-Version: 2.1
Name: colorir
Version: 2.0.5
Summary: A python package for easy management of colors and palettes.
Home-page: https://github.com/aleferna12/colorir
Author: aleferna
Author-email: alexandrepchfernandes@gmail.com
License: MIT
Project-URL: Documentation, https://colorir.readthedocs.io/en/latest/
Requires-Python: >=3.8
License-File: LICENSE.txt
Requires-Dist: numpy
Requires-Dist: networkx
